unified/__init__.py
unified/__main__.py
unified/cli.py
unified/paths.py
unified/services.py
unified/web.py
unified/core/__init__.py
unified/core/memory.py
unified/core/registry.py
unified/governance/__init__.py
unified/governance/audit.py
unified/governance/evaluator.py
unified/models/__init__.py
unified/models/base.py
unified/models/claude.py
unified/models/gemini_adapter.py
unified/models/ollama.py
unified/models/openai_adapter.py
unified/resources/checklists/ai_output_review.md
unified/resources/checklists/architecture_review.md
unified/resources/checklists/code_review.md
unified/resources/checklists/release_readiness.md
unified/resources/configs/registry.yaml
unified/supporting/__init__.py
unified/supporting/context.py
unified/supporting/router.py
unified/tools/__init__.py
unified/tools/files.py
unified/tools/testing.py
unified_controlplane-0.3.0.dist-info/METADATA
unified_controlplane-0.3.0.dist-info/WHEEL
unified_controlplane-0.3.0.dist-info/entry_points.txt
unified_controlplane-0.3.0.dist-info/licenses/LICENSE
unified_controlplane-0.3.0.dist-info/RECORD
