Metadata-Version: 2.4
Name: unified-controlplane
Version: 0.3.0
Summary: AI Control Plane for orchestrating models, memory, and evaluation
Author: Jack Blacketter
License-Expression: MIT
License-File: LICENSE
Requires-Python: >=3.10
Requires-Dist: click>=8.0
Requires-Dist: httpx>=0.25
Requires-Dist: importlib-resources>=5.0; python_version < '3.11'
Requires-Dist: pyyaml>=6.0
Provides-Extra: all
Requires-Dist: anthropic>=0.18; extra == 'all'
Requires-Dist: google-generativeai>=0.3; extra == 'all'
Requires-Dist: openai>=1.0; extra == 'all'
Provides-Extra: claude
Requires-Dist: anthropic>=0.18; extra == 'claude'
Provides-Extra: dev
Requires-Dist: pytest-cov; extra == 'dev'
Requires-Dist: pytest>=7.0; extra == 'dev'
Provides-Extra: gemini
Requires-Dist: google-generativeai>=0.3; extra == 'gemini'
Provides-Extra: openai
Requires-Dist: openai>=1.0; extra == 'openai'
